lazyedit/__about__.py
lazyedit/__init__.py
lazyedit/directory.py
lazyedit/fileEditor.py
lazyedit/gui.py
lazyedit/lazydocker_screen.py
lazyedit/lazygit_screen.py
lazyedit/terminal.py
lazyedit-0.1.4.dist-info/METADATA
lazyedit-0.1.4.dist-info/WHEEL
lazyedit-0.1.4.dist-info/entry_points.txt
lazyedit-0.1.4.dist-info/licenses/LICENSE.txt
lazyedit-0.1.4.dist-info/RECORD
