Metadata-Version: 2.4
Name: lazyedit
Version: 0.1.4
Summary: A textual-based lazy editing tool
Project-URL: Documentation, https://github.com/Robbevanherpe1/lazyedit#readme
Project-URL: Issues, https://github.com/Robbevanherpe1/lazyedit/issues
Project-URL: Source, https://github.com/Robbevanherpe1/lazyedit
Author-email: Robbe <robbe.vanherpe04@yahoo.com>
License: MIT License
License-File: LICENSE.txt
Classifier: Development Status :: 4 - Beta
Classifier: Operating System :: Microsoft :: Windows
Classifier: Programming Language :: Python
Classifier: Programming Language :: Python :: 3.10
Classifier: Programming Language :: Python :: Implementation :: CPython
Classifier: Programming Language :: Python :: Implementation :: PyPy
Requires-Python: >=3.8
Requires-Dist: keyboard>=0.13.5
Requires-Dist: rich>=13.0.0
Requires-Dist: textual==0.47.1
